LeoLeeeCommon/__init__.py
LeoLeeeCommon/version.py
LeoLeeeCommon/utils/__init__.py
LeoLeeeCommon/utils/db.py
LeoLeeeCommon/utils/flask_tool.py
LeoLeeeCommon/utils/log.py
common/__init__.py
common/version.py
common/utils/__init__.py
common/utils/db.py
common/utils/flask_tool.py
common/utils/log.py
LeoLeeeCommon-0.1.5.dist-info/METADATA
LeoLeeeCommon-0.1.5.dist-info/WHEEL
LeoLeeeCommon-0.1.5.dist-info/top_level.txt
LeoLeeeCommon-0.1.5.dist-info/RECORD
