Metadata-Version: 2.1
Name: LeoLeeeCommon
Version: 0.1.5
Summary: leo leee common library
Home-page: http://github.com/LeoLeeeCommon/LeoLeeeCommon
Author: LeoLeee
Author-email: 493671495@qq.com
License: MIT
Requires-Dist: PyYAML
Requires-Dist: sqlalchemy
